LICENSE
MANIFEST.in
README.md
setup.cfg
setup.py
kelectric/__init__.py
kelectric/bd.py
kelectric/kelectric.py
kelectric.egg-info/PKG-INFO
kelectric.egg-info/SOURCES.txt
kelectric.egg-info/dependency_links.txt
kelectric.egg-info/requires.txt
kelectric.egg-info/top_level.txt